COPYING
COPYING.LESSER
MANIFEST.in
README.md
setup.py
genpipes/__init__.py
genpipes/__main__.py
genpipes/version.py
genpipes/bfx/__init__.py
genpipes/bfx/adapters.py
genpipes/bfx/amber.py
genpipes/bfx/annotations.py
genpipes/bfx/artic.py
genpipes/bfx/ballgown.py
genpipes/bfx/bamreadcount.py
genpipes/bfx/bash_cmd.py
genpipes/bfx/bcbio_variation_recall.py
genpipes/bfx/bcftools.py
genpipes/bfx/bed_file.py
genpipes/bfx/bedops.py
genpipes/bfx/bedtools.py
genpipes/bfx/bigwiginfo.py
genpipes/bfx/bismark.py
genpipes/bfx/bissnp.py
genpipes/bfx/blast.py
genpipes/bfx/blat.py
genpipes/bfx/breakseq2.py
genpipes/bfx/bvatools.py
genpipes/bfx/bwa.py
genpipes/bfx/bwakit.py
genpipes/bfx/chicago.py
genpipes/bfx/chromimpute.py
genpipes/bfx/circlator.py
genpipes/bfx/cnvkit.py
genpipes/bfx/cobalt.py
genpipes/bfx/conpair.py
genpipes/bfx/covseq_tools.py
genpipes/bfx/cufflinks.py
genpipes/bfx/cutadapt.py
genpipes/bfx/dada2.py
genpipes/bfx/deliverables.py
genpipes/bfx/delly.py
genpipes/bfx/design.py
genpipes/bfx/differential_binding.py
genpipes/bfx/differential_expression.py
genpipes/bfx/dna_damage.py
genpipes/bfx/epigeec.py
genpipes/bfx/epiqc_reports.py
genpipes/bfx/exonerate.py
genpipes/bfx/fastqc.py
genpipes/bfx/fgbio.py
genpipes/bfx/flash.py
genpipes/bfx/freebayes.py
genpipes/bfx/gatk.py
genpipes/bfx/gatk4.py
genpipes/bfx/gemini.py
genpipes/bfx/genome.py
genpipes/bfx/gq_seq_utils.py
genpipes/bfx/guppy.py
genpipes/bfx/hic.py
genpipes/bfx/hicplotter.py
genpipes/bfx/hicrep.py
genpipes/bfx/hicup.py
genpipes/bfx/homer.py
genpipes/bfx/htseq.py
genpipes/bfx/htslib.py
genpipes/bfx/igvtools.py
genpipes/bfx/ivar.py
genpipes/bfx/jsonator.py
genpipes/bfx/kraken2.py
genpipes/bfx/krona.py
genpipes/bfx/lumpy.py
genpipes/bfx/macs2.py
genpipes/bfx/manta.py
genpipes/bfx/metasv.py
genpipes/bfx/metric_tools.py
genpipes/bfx/metrics.py
genpipes/bfx/minimap2.py
genpipes/bfx/multiqc.py
genpipes/bfx/mummer.py
genpipes/bfx/ncovtools.py
genpipes/bfx/ngscheckmate.py
genpipes/bfx/pacbio_tools.py
genpipes_suite.egg-info/PKG-INFO
genpipes_suite.egg-info/SOURCES.txt
genpipes_suite.egg-info/dependency_links.txt
genpipes_suite.egg-info/entry_points.txt
genpipes_suite.egg-info/requires.txt
genpipes_suite.egg-info/top_level.txt